tf_utils/__init__.py
tf_utils/custom_losses.py
tf_utils/debug.py
tf_utils/gail_dataset.py
tf_utils/gail_utils.py
tf_utils/improved_wasserstein.py
tf_utils/math_functions.py
tf_utils/plot.py
tf_utils/statistics.py
tf_utils/tf_utils.py
tf_utils/wrappers/__init__.py
tf_utils/wrappers/atariActionWrapper.py
tf_utils/wrappers/atari_wrappers_utils.py
tf_utils-1.0.4.dist-info/LICENSE
tf_utils-1.0.4.dist-info/METADATA
tf_utils-1.0.4.dist-info/WHEEL
tf_utils-1.0.4.dist-info/top_level.txt
tf_utils-1.0.4.dist-info/RECORD
