Metadata-Version: 2.1
Name: tf-utils
Version: 1.0.4
Summary: TensorFlow utils for Generative Adversarial Imitaion Learning
Home-page: UNKNOWN
Author: Sergiy Isakov
Author-email: marvine.si@gmail.com
License: UNKNOWN
Platform: UNKNOWN
Classifier: Programming Language :: Python :: 3
Classifier: License :: OSI Approved :: MIT License
Classifier: Operating System :: OS Independent
